infinite_context/__init__.py
infinite_context/infinite_context.py
infinite_context-4.0.2.dist-info/LICENSE.txt
infinite_context-4.0.2.dist-info/METADATA
infinite_context-4.0.2.dist-info/WHEEL
infinite_context-4.0.2.dist-info/top_level.txt
infinite_context-4.0.2.dist-info/RECORD
