Metadata-Version: 2.2
Name: infinite_context
Version: 4.0.2
Home-page: https://github.com/sapiens-technology/InfiniteContext
Author: SAPIENS TECHNOLOGY
License: Proprietary Software
License-File: LICENSE.txt
Requires-Dist: perpetual-context
Requires-Dist: certifi
Requires-Dist: requests
Requires-Dist: lxml
Requires-Dist: pandas
Requires-Dist: pillow
Requires-Dist: numpy
Requires-Dist: paddlepaddle
Requires-Dist: paddleocr
Requires-Dist: opencv-python
Requires-Dist: moviepy
Requires-Dist: SpeechRecognition
Requires-Dist: ffmpeg-python
Requires-Dist: pydub
Requires-Dist: docx2txt
Requires-Dist: youtube-transcript-extractor
Dynamic: author
Dynamic: home-page
Dynamic: license
Dynamic: requires-dist
